{
    "photo0": "http://lorempixel.com/400/200/abstract",
    "photo1": "http://lorempixel.com/400/200/abstract",
    "photo2": "http://lorempixel.com/400/200/abstract",
    "photo3": "http://lorempixel.com/400/200/abstract",
    "photo4": "http://lorempixel.com/400/200/abstract",
    "photo5": "http://lorempixel.com/400/200/abstract",
    "photo6": "http://lorempixel.com/400/200/abstract",
    "photo7": "http://lorempixel.com/400/200/abstract",
    "photo8": "http://lorempixel.com/400/200/abstract",
    "photo9": "http://lorempixel.com/400/200/abstract",
    "photo10": "http://lorempixel.com/400/200/abstract",
    "photo11": "http://lorempixel.com/400/200/abstract",
    "photo12": "http://lorempixel.com/400/200/abstract",
    "photo13": "http://lorempixel.com/400/200/abstract",
    "photo14": "http://lorempixel.com/400/200/abstract",
    "photo15": "http://lorempixel.com/400/200/abstract",
    "photo16": "http://lorempixel.com/400/200/abstract",
    "photo17": "http://lorempixel.com/400/200/abstract",
    "photo18": "http://lorempixel.com/400/200/abstract",
    "photo19": "http://lorempixel.com/400/200/abstract"
}